{"cameraMode":{"drawMode":0,"name":"Shaded","section":"Shading Mode"},"sceneLighting":true,"audioPlay":false,"sceneViewState":{"m_AlwaysRefresh":false,"showFog":true,"showSkybox":true,"showFlares":true,"showImageEffects":true,"showParticleSystems":true,"showVisualEffectGraphs":true,"m_FxEnabled":true},"in2DMode":false,"pivot":{"x":-3.385618209838867,"y":0.4871034622192383,"z":4.202846527099609},"rotation":{"x":-0.11084390431642533,"y":0.8363639116287231,"z":-0.18378907442092896,"w":-0.5044150352478027},"size":10.0,"orthographic":false}